grblas/__init__.py
grblas/_agg.py
grblas/_automethods.py
grblas/_infixmethods.py
grblas/_slice.py
grblas/_version.py
grblas/agg.py
grblas/base.py
grblas/descriptor.py
grblas/dtypes.py
grblas/exceptions.py
grblas/expr.py
grblas/formatting.py
grblas/grblas.yaml
grblas/infix.py
grblas/io.py
grblas/mask.py
grblas/matrix.py
grblas/operator.py
grblas/recorder.py
grblas/scalar.py
grblas/utils.py
grblas/vector.py
grblas/_ss/__init__.py
grblas/_ss/matrix.py
grblas/_ss/prefix_scan.py
grblas/_ss/utils.py
grblas/_ss/vector.py
grblas/binary/__init__.py
grblas/binary/numpy.py
grblas/monoid/__init__.py
grblas/monoid/numpy.py
grblas/op/__init__.py
grblas/op/numpy.py
grblas/semiring/__init__.py
grblas/semiring/numpy.py
grblas/ss/__init__.py
grblas/ss/_core.py
grblas/tests/__init__.py
grblas/tests/conftest.py
grblas/tests/pickle1.pkl
grblas/tests/pickle2.pkl
grblas/tests/test_auto_init.py
grblas/tests/test_core.py
grblas/tests/test_descriptor.py
grblas/tests/test_dtype.py
grblas/tests/test_external_init.py
grblas/tests/test_formatting.py
grblas/tests/test_infix.py
grblas/tests/test_io.py
grblas/tests/test_matrix.py
grblas/tests/test_numpyops.py
grblas/tests/test_op.py
grblas/tests/test_operator_types.py
grblas/tests/test_pickle.py
grblas/tests/test_prefix_scan.py
grblas/tests/test_pygraphblas.py
grblas/tests/test_recorder.py
grblas/tests/test_resolving.py
grblas/tests/test_scalar.py
grblas/tests/test_ss_utils.py
grblas/tests/test_vector.py
grblas/unary/__init__.py
grblas/unary/numpy.py
grblas-2022.4.0.1.dist-info/LICENSE
grblas-2022.4.0.1.dist-info/METADATA
grblas-2022.4.0.1.dist-info/WHEEL
grblas-2022.4.0.1.dist-info/top_level.txt
grblas-2022.4.0.1.dist-info/RECORD
