Metadata-Version: 2.1
Name: grblas
Version: 2022.4.0.1
Summary: Python interface to GraphBLAS
Home-page: https://github.com/metagraph-dev/grblas
Author: Jim Kitchen and Erik Welch
Author-email: erik.n.welch@gmail.com,jim22k@gmail.com
License: Apache License 2.0
Keywords: graphblas,graph,sparse,matrix,lagraph,suitesparse
Classifier: Development Status :: 4 - Beta
Classifier: License :: OSI Approved :: Apache Software License
Classifier: Operating System :: MacOS :: MacOS X
Classifier: Operating System :: POSIX :: Linux
Classifier: Operating System :: Microsoft :: Windows
Classifier: Programming Language :: Python
Classifier: Programming Language :: Python :: 3
Classifier: Programming Language :: Python :: 3.8
Classifier: Programming Language :: Python :: 3.9
Classifier: Programming Language :: Python :: 3.10
Classifier: Programming Language :: Python :: 3 :: Only
Classifier: Intended Audience :: Developers
Classifier: Intended Audience :: Science/Research
Classifier: Topic :: Scientific/Engineering
Classifier: Topic :: Scientific/Engineering :: Mathematics
Requires-Python: >=3.8
License-File: LICENSE
Requires-Dist: suitesparse-graphblas (<6.3,>=6.0)
Requires-Dist: numba
Requires-Dist: donfig
Requires-Dist: pyyaml
Provides-Extra: complete
Requires-Dist: matplotlib ; extra == 'complete'
Requires-Dist: networkx ; extra == 'complete'
Requires-Dist: pandas ; extra == 'complete'
Requires-Dist: scipy ; extra == 'complete'
Provides-Extra: io
Requires-Dist: networkx ; extra == 'io'
Requires-Dist: scipy ; extra == 'io'
Provides-Extra: repr
Requires-Dist: pandas ; extra == 'repr'
Provides-Extra: viz
Requires-Dist: matplotlib ; extra == 'viz'
